<?xml version="1.0" encoding="utf-8"?>
	<annotation>
		<folder>G:\datasets\paperdatasets_0419\images\train</folder>
		<filename>image_MWBAzv.jpg</filename>
		<size>
			<width>1440</width>
			<height>1080</height>
			<depth>3</depth>
		</size>
		<object>
			<name>halt</name>
			<pose>Unspecified</pose>
			<truncated>0</truncated>
			<difficult>0</difficult>
			<bndbox>
				<xmin>510</xmin>
				<ymin>392</ymin>
				<xmax>572</xmax>
				<ymax>456</ymax>
			</bndbox>
		</object>
		<object>
			<name>halt</name>
			<pose>Unspecified</pose>
			<truncated>0</truncated>
			<difficult>0</difficult>
			<bndbox>
				<xmin>613</xmin>
				<ymin>162</ymin>
				<xmax>676</xmax>
				<ymax>223</ymax>
			</bndbox>
		</object>
		<object>
			<name>halt</name>
			<pose>Unspecified</pose>
			<truncated>0</truncated>
			<difficult>0</difficult>
			<bndbox>
				<xmin>3</xmin>
				<ymin>437</ymin>
				<xmax>30</xmax>
				<ymax>481</ymax>
			</bndbox>
		</object>
		<object>
			<name>inear</name>
			<pose>Unspecified</pose>
			<truncated>0</truncated>
			<difficult>0</difficult>
			<bndbox>
				<xmin>539</xmin>
				<ymin>425</ymin>
				<xmax>568</xmax>
				<ymax>458</ymax>
			</bndbox>
		</object>
	</annotation>
