<?xml version="1.0" encoding="utf-8"?>
	<annotation>
		<folder>G:\datasets\paperdatasets_0419\images\train</folder>
		<filename>image_tbfhWC.jpg</filename>
		<size>
			<width>960</width>
			<height>720</height>
			<depth>3</depth>
		</size>
		<object>
			<name>halt</name>
			<pose>Unspecified</pose>
			<truncated>0</truncated>
			<difficult>0</difficult>
			<bndbox>
				<xmin>277</xmin>
				<ymin>196</ymin>
				<xmax>358</xmax>
				<ymax>284</ymax>
			</bndbox>
		</object>
		<object>
			<name>halt</name>
			<pose>Unspecified</pose>
			<truncated>0</truncated>
			<difficult>0</difficult>
			<bndbox>
				<xmin>554</xmin>
				<ymin>242</ymin>
				<xmax>613</xmax>
				<ymax>293</ymax>
			</bndbox>
		</object>
		<object>
			<name>inear</name>
			<pose>Unspecified</pose>
			<truncated>0</truncated>
			<difficult>0</difficult>
			<bndbox>
				<xmin>295</xmin>
				<ymin>233</ymin>
				<xmax>328</xmax>
				<ymax>273</ymax>
			</bndbox>
		</object>
	</annotation>
