<?xml version="1.0" encoding="utf-8"?>
	<annotation>
		<folder>G:\datasets\paperdatasets_0419\images\train</folder>
		<filename>image_vejFZP.jpg</filename>
		<size>
			<width>1080</width>
			<height>1920</height>
			<depth>3</depth>
		</size>
		<object>
			<name>halt</name>
			<pose>Unspecified</pose>
			<truncated>0</truncated>
			<difficult>0</difficult>
			<bndbox>
				<xmin>426</xmin>
				<ymin>205</ymin>
				<xmax>453</xmax>
				<ymax>239</ymax>
			</bndbox>
		</object>
		<object>
			<name>halt</name>
			<pose>Unspecified</pose>
			<truncated>0</truncated>
			<difficult>0</difficult>
			<bndbox>
				<xmin>983</xmin>
				<ymin>1352</ymin>
				<xmax>1039</xmax>
				<ymax>1406</ymax>
			</bndbox>
		</object>
		<object>
			<name>halt</name>
			<pose>Unspecified</pose>
			<truncated>0</truncated>
			<difficult>0</difficult>
			<bndbox>
				<xmin>799</xmin>
				<ymin>1295</ymin>
				<xmax>835</xmax>
				<ymax>1343</ymax>
			</bndbox>
		</object>
	</annotation>
